pybedlite/__init__.py
pybedlite/bed_record.py
pybedlite/bed_source.py
pybedlite/bed_writer.py
pybedlite/overlap_detector.py
pybedlite/py.typed
pybedlite-1.1.0.dist-info/METADATA
pybedlite-1.1.0.dist-info/WHEEL
pybedlite-1.1.0.dist-info/licenses/LICENSE
pybedlite-1.1.0.dist-info/RECORD
