Metadata-Version: 2.4
Name: pybedlite
Version: 1.1.0
Summary: Lightweight Python interfaces for reading, writing, and querying genomic regions (BED)
Project-URL: Bug Tracker, https://github.com/fulcrumgenomics/pybedlite/issues
Project-URL: Documentation, https://pybedlite.readthedocs.io
Project-URL: Homepage, https://github.com/fulcrumgenomics/pybedlite
Project-URL: Repository, https://github.com/fulcrumgenomics/pybedlite
Author-email: Clint Valentine <clint@fulcrumgenomics.com>, Nils Homer <nils@fulcrumgenomics.com>, Tim Fennell <tim@fulcrumgenomics.com>
License-Expression: MIT
License-File: LICENSE
Classifier: Development Status :: 4 - Beta
Classifier: Intended Audience :: Developers
Classifier: Intended Audience :: Science/Research
Classifier: License :: OSI Approved :: MIT License
Classifier: Natural Language :: English
Classifier: Operating System :: OS Independent
Classifier: Programming Language :: Python :: 3
Classifier: Programming Language :: Python :: 3.9
Classifier: Programming Language :: Python :: 3.10
Classifier: Programming Language :: Python :: 3.11
Classifier: Programming Language :: Python :: 3.12
Classifier: Programming Language :: Python :: 3.13
Classifier: Typing :: Typed
Requires-Python: <4.0,>=3.9
Requires-Dist: attrs~=23.0
Requires-Dist: superintervals~=0.2.10
